zodable_sample_package/__init__.py
zodable_sample_package/py.typed
zodable_sample_package/digital/guimauve/example/Address.py
zodable_sample_package/digital/guimauve/example/Country.py
zodable_sample_package/digital/guimauve/example/Custom.py
zodable_sample_package/digital/guimauve/example/Message.py
zodable_sample_package/digital/guimauve/example/Payload.py
zodable_sample_package/digital/guimauve/example/User.py
zodable_sample_package-1.6.0.dist-info/METADATA
zodable_sample_package-1.6.0.dist-info/WHEEL
zodable_sample_package-1.6.0.dist-info/top_level.txt
zodable_sample_package-1.6.0.dist-info/RECORD
