Metadata-Version: 2.4
Name: zodable-sample-package
Version: 1.6.0
Summary: Auto-generated Pydantic project from Kotlin using guimauvedigital/zodable
Requires-Python: >=3.9
Requires-Dist: pydantic
Requires-Dist: typing
Requires-Dist: zodable-idschema
Requires-Dist: zodable-sample-package-multiplatform
Requires-Dist: uuid
Requires-Dist: zodable-kotlin-primitives
Requires-Dist: datetime
